py_sql/__init__.py
py_sql/py_sql.py
py_sql-1.0.0.dist-info/METADATA
py_sql-1.0.0.dist-info/WHEEL
py_sql-1.0.0.dist-info/top_level.txt
py_sql-1.0.0.dist-info/RECORD
